quotescape/__init__.py
quotescape/cli.py
quotescape/assets/__init__.py
quotescape/assets/default-dark-mode-book-cover.png
quotescape/assets/default-light-mode-book-cover.png
quotescape/assets/fonts/B612-Italic.ttf
quotescape/assets/fonts/B612-Regular.ttf
quotescape/assets/fonts/__init__.py
quotescape/parsers/__init__.py
quotescape/parsers/yamlconfig.py
quotescape/quotes/__init__.py
quotescape/quotes/custom.py
quotescape/quotes/kindle.py
quotescape/quotes/random.py
quotescape/render/__init__.py
quotescape/render/wallpaper.py
quotescape-1.0.2.dist-info/licenses/LICENSE
quotescape-1.0.2.dist-info/METADATA
quotescape-1.0.2.dist-info/WHEEL
quotescape-1.0.2.dist-info/entry_points.txt
quotescape-1.0.2.dist-info/top_level.txt
quotescape-1.0.2.dist-info/RECORD
