Metadata-Version: 2.4
Name: quotescape
Version: 1.0.2
Summary: Create wallpapers from quotes - Kindle highlights (2FA-aware, multi-browser), custom lists, or random ones - and set them as your desktop background.
Requires-Python: >=3.11
License-File: LICENSE
Requires-Dist: pillow>=11.3.0
Requires-Dist: pyyaml>=6.0.2
Requires-Dist: requests>=2.32.4
Requires-Dist: selenium>=4.34.2
Dynamic: license-file
